BSenti/__init__.py
BSenti/dataset.py
BSenti/pretrained_models.py
BSenti-0.0.1.dist-info/LICENSE.txt
BSenti-0.0.1.dist-info/METADATA
BSenti-0.0.1.dist-info/WHEEL
BSenti-0.0.1.dist-info/top_level.txt
BSenti-0.0.1.dist-info/RECORD
