Metadata-Version: 2.1
Name: BSenti
Version: 0.0.1
Summary: BSenti: Sentiment Classification Library
Author: Saadat (Saadat Rafid Ahmed)
Author-email: <saadat.r.ahmed@gmail.com>
Keywords: python,sentiment classification,nlp
Classifier: Development Status :: 1 - Planning
Classifier: Intended Audience :: Developers
Classifier: Programming Language :: Python :: 3
Classifier: Operating System :: Unix
Classifier: Operating System :: MacOS :: MacOS X
Classifier: Operating System :: Microsoft :: Windows
License-File: LICENSE.txt
Requires-Dist: pandas
Requires-Dist: joblib
Requires-Dist: scikit-learn
